Metadata-Version: 2.1
Name: astersay
Version: 0.24.2
Summary: This is a Python library for Asterisk to work with Yandex voice models.
Home-page: https://gitlab.com/djbaldey/asterisk-dialogs/
Author: Grigoriy Kramarenko
Author-email: root@rosix.ru
License: BSD License
Platform: any
Classifier: Development Status :: 5 - Production/Stable
Classifier: Environment :: Console
Classifier: Intended Audience :: Developers
Classifier: Intended Audience :: Telecommunications Industry
Classifier: License :: OSI Approved :: BSD License
Classifier: Natural Language :: Russian
Classifier: Operating System :: POSIX
Classifier: Operating System :: POSIX :: Linux
Classifier: Programming Language :: Python
Classifier: Programming Language :: Python :: 3.5
Classifier: Programming Language :: Python :: 3.6
Classifier: Programming Language :: Python :: 3.7
Classifier: Programming Language :: Python :: 3.8
Classifier: Topic :: Communications :: Internet Phone
Classifier: Topic :: Communications :: Telephony
Requires-Dist: grpcio (<1.28.0a,>=1.27.2)
Requires-Dist: protobuf (<3.15.0a,>=3.12.0)
Requires-Dist: pyjwt[crypto] (<2.1a,>=1.6.4)
Requires-Dist: pymorphy2 (<1.0a,>=0.8)
Requires-Dist: python-dateutil (<3.0a,>=2.6.1)
Requires-Dist: requests (<3.0a,>=2.18.3)
Requires-Dist: unidecode (<2.0a,>=1.0)
Provides-Extra: dev
Requires-Dist: pyaudio (<1.0a,>=0.2.11) ; extra == 'dev'
Requires-Dist: websocket-client (<1.0a,>=0.50.0) ; extra == 'dev'
